larf_weather_sse/__init__.py
larf_weather_sse/main.py
larf_weather_sse/server.py
larf_weather_sse-0.1.0.dist-info/METADATA
larf_weather_sse-0.1.0.dist-info/WHEEL
larf_weather_sse-0.1.0.dist-info/entry_points.txt
larf_weather_sse-0.1.0.dist-info/top_level.txt
larf_weather_sse-0.1.0.dist-info/RECORD
