Metadata-Version: 2.4
Name: larf-weather-sse
Version: 0.1.0
Summary: Query the city of the weather
Requires-Python: >=3.13
Requires-Dist: httpx>=0.28.1
Requires-Dist: mcp>=1.15.0
